llama_index/graph_stores/ApertureDB/__init__.py
llama_index/graph_stores/ApertureDB/property_graph.py
llama_index_graph_stores_aperturedb-0.2.1.dist-info/METADATA
llama_index_graph_stores_aperturedb-0.2.1.dist-info/WHEEL
llama_index_graph_stores_aperturedb-0.2.1.dist-info/licenses/LICENSE
llama_index_graph_stores_aperturedb-0.2.1.dist-info/RECORD
