Metadata-Version: 2.4
Name: llama-index-graph-stores-ApertureDB
Version: 0.2.1
Summary: llama-index graph stores ApertureDB integration
Author-email: ApertureData <team@aperturedata.io>
License-Expression: MIT
License-File: LICENSE
Requires-Python: <4.0,>=3.9
Requires-Dist: aperturedb>=0.4.46
Requires-Dist: llama-index-core<0.15,>=0.13.0
